setup.py
abc_distributions/Binomialdistribution.py
abc_distributions/Gaussiandistribution.py
abc_distributions/Generaldistribution.py
abc_distributions/__init__.py
abc_distributions.egg-info/PKG-INFO
abc_distributions.egg-info/SOURCES.txt
abc_distributions.egg-info/dependency_links.txt
abc_distributions.egg-info/not-zip-safe
abc_distributions.egg-info/top_level.txt